LICENSE
MANIFEST.in
README.md
pyproject.toml
setup.py
berryimu/CMakeLists.txt
berryimu/__init__.py
berryimu/__init__.pyi
berryimu/cli.py
berryimu/cli.pyi
berryimu/py.typed
berryimu/requirements-dev.txt
berryimu/requirements.txt
berryimu.egg-info/PKG-INFO
berryimu.egg-info/SOURCES.txt
berryimu.egg-info/dependency_links.txt
berryimu.egg-info/entry_points.txt
berryimu.egg-info/requires.txt
berryimu.egg-info/top_level.txt
berryimu/imu/CMakeLists.txt
berryimu/imu/LIS3MDL.h
berryimu/imu/LSM6DSL.h
berryimu/imu/LSM9DS0.h
berryimu/imu/LSM9DS1.h
berryimu/imu/__init__.py
berryimu/imu/__init__.pyi
berryimu/imu/i2c-dev.h
berryimu/imu/imu.cpp
berryimu/imu/imu.h
berryimu/imu/imu.pyi
berryimu/imu/imu.so
tests/test_dummy.py