Metadata-Version: 2.1
Name: berryimu
Version: 0.0.1
Summary: C++ bindings for controlling the BerryIMU
Home-page: https://github.com/kscalelabs/berryimu
Author: Benjamin Bolte
Requires-Python: >=3.9
License-File: LICENSE
Provides-Extra: dev
Requires-Dist: black; extra == "dev"
Requires-Dist: darglint; extra == "dev"
Requires-Dist: mypy; extra == "dev"
Requires-Dist: pytest; extra == "dev"
Requires-Dist: ruff; extra == "dev"
